odoo/addons/quality_control_mrp_oca/README.rst
odoo/addons/quality_control_mrp_oca/__init__.py
odoo/addons/quality_control_mrp_oca/__manifest__.py
odoo/addons/quality_control_mrp_oca/data/quality_control_mrp_data.xml
odoo/addons/quality_control_mrp_oca/i18n/ca.po
odoo/addons/quality_control_mrp_oca/i18n/de.po
odoo/addons/quality_control_mrp_oca/i18n/el_GR.po
odoo/addons/quality_control_mrp_oca/i18n/es.po
odoo/addons/quality_control_mrp_oca/i18n/es_ES.po
odoo/addons/quality_control_mrp_oca/i18n/es_MX.po
odoo/addons/quality_control_mrp_oca/i18n/eu.po
odoo/addons/quality_control_mrp_oca/i18n/fi.po
odoo/addons/quality_control_mrp_oca/i18n/fr.po
odoo/addons/quality_control_mrp_oca/i18n/fr_CH.po
odoo/addons/quality_control_mrp_oca/i18n/fr_FR.po
odoo/addons/quality_control_mrp_oca/i18n/gl.po
odoo/addons/quality_control_mrp_oca/i18n/hr.po
odoo/addons/quality_control_mrp_oca/i18n/hr_HR.po
odoo/addons/quality_control_mrp_oca/i18n/it.po
odoo/addons/quality_control_mrp_oca/i18n/nl.po
odoo/addons/quality_control_mrp_oca/i18n/nl_NL.po
odoo/addons/quality_control_mrp_oca/i18n/pt.po
odoo/addons/quality_control_mrp_oca/i18n/pt_BR.po
odoo/addons/quality_control_mrp_oca/i18n/quality_control_mrp_oca.pot
odoo/addons/quality_control_mrp_oca/i18n/ro.po
odoo/addons/quality_control_mrp_oca/i18n/ru.po
odoo/addons/quality_control_mrp_oca/i18n/sk.po
odoo/addons/quality_control_mrp_oca/i18n/sl.po
odoo/addons/quality_control_mrp_oca/i18n/tr.po
odoo/addons/quality_control_mrp_oca/i18n/tr_TR.po
odoo/addons/quality_control_mrp_oca/i18n/vi_VN.po
odoo/addons/quality_control_mrp_oca/i18n/zh_CN.po
odoo/addons/quality_control_mrp_oca/models/__init__.py
odoo/addons/quality_control_mrp_oca/models/mrp_production.py
odoo/addons/quality_control_mrp_oca/models/qc_inspection.py
odoo/addons/quality_control_mrp_oca/readme/CONTRIBUTORS.rst
odoo/addons/quality_control_mrp_oca/readme/DESCRIPTION.rst
odoo/addons/quality_control_mrp_oca/static/description/icon.png
odoo14_addon_quality_control_mrp_oca-14.0.1.0.1.dev8.dist-info/METADATA
odoo14_addon_quality_control_mrp_oca-14.0.1.0.1.dev8.dist-info/WHEEL
odoo14_addon_quality_control_mrp_oca-14.0.1.0.1.dev8.dist-info/top_level.txt
odoo14_addon_quality_control_mrp_oca-14.0.1.0.1.dev8.dist-info/RECORD
