Metadata-Version: 2.1
Name: odoo14-addon-quality_control_mrp_oca
Version: 14.0.1.0.1.dev8
Summary: MRP extension for quality control (OCA)
Home-page: https://github.com/OCA/manufacture
Author: OdooMRP team, AvanzOSC, Serv. Tecnol. Avanzados - Pedro M. Baeza, Agile Business Group, Odoo Community Association (OCA)
Author-email: support@odoo-community.org
License: AGPL-3
Classifier: Programming Language :: Python
Classifier: Framework :: Odoo
Classifier: Framework :: Odoo :: 14.0
Classifier: License :: OSI Approved :: GNU Affero General Public License v3
Requires-Python: >=3.6
Requires-Dist: odoo14-addon-quality-control-oca
Requires-Dist: odoo14-addon-quality-control-stock-oca
Requires-Dist: odoo<14.1dev,>=14.0a
